image_processing/__init__.py
image_processing/processing/__init__.py
image_processing/processing/combination.py
image_processing/processing/transformation.py
image_processing/utils/__init__.py
image_processing/utils/io.py
image_processing/utils/plot.py
bruno_image_processing-0.0.3.dist-info/METADATA
bruno_image_processing-0.0.3.dist-info/WHEEL
bruno_image_processing-0.0.3.dist-info/top_level.txt
bruno_image_processing-0.0.3.dist-info/RECORD
