Metadata-Version: 2.1
Name: bruno-image-processing
Version: 0.0.3
Summary: Pacote cirado com intruções da DIO
Author: Bruno Carvalho
Author-email: brunoandradecarvalho2@gmail.com
Requires-Python: >=3.8
Requires-Dist: Matplotlib
Requires-Dist: scikit-image
